dekimashita/__init__.py
dekimashita/dekimashita.py
dekimashita-0.0.4.dist-info/LICENSE
dekimashita-0.0.4.dist-info/METADATA
dekimashita-0.0.4.dist-info/WHEEL
dekimashita-0.0.4.dist-info/top_level.txt
dekimashita-0.0.4.dist-info/RECORD
