Metadata-Version: 2.1
Name: dekimashita
Version: 0.0.4
Summary: Library designed to process text with various filter criteria
Author: ryyos (Rio Dwi Saputra)
Author-email: <riodwi12174@gmail.com>
Keywords: filter,dictionary,text,textCleaning,alphabetic
Classifier: Development Status :: 1 - Planning
Classifier: Intended Audience :: Developers
Classifier: Programming Language :: Python
Classifier: Operating System :: Microsoft :: Windows
License-File: LICENSE
